{
  "cli": {
    "version": ">= 7.6.0",
    "appVersionSource": "remote"
  },
  "build": {
    "preview": {
      "distribution": "internal",
      "android": {
        "buildType": "apk"
      },
      "env": {
        "EXPO_PUBLIC_API_URL": "https://tarot-back-production-5631.up.railway.app/api",
        "EXPO_PUBLIC_WEB_URL": "https://app.locosxpadel.com/tarot_arcano/",
        "EXPO_PUBLIC_WSS_URL": "https://tarot-back-production-5631.up.railway.app"
      }
    },
    "production": {
      "distribution": "internal",
      "android": {
        "buildType": "app-bundle"
      }
    }
  },
  "submit": {
    "production": {}
  }
}
